bad/__init__.py
bad/filtered.py
bad/grep.py
bad/numeric.py
bad/undeletable.py
bad_ideas-0.0.2.dist-info/DESCRIPTION.rst
bad_ideas-0.0.2.dist-info/METADATA
bad_ideas-0.0.2.dist-info/RECORD
bad_ideas-0.0.2.dist-info/WHEEL
bad_ideas-0.0.2.dist-info/metadata.json
bad_ideas-0.0.2.dist-info/top_level.txt
