Metadata-Version: 2.0
Name: bad-ideas
Version: 0.0.2
Summary: Pythonic Redis Client.
Home-page: https://github.com/seperman/bad-ideas
Author: Seperman
Author-email: sep@zepworks.com
License: MIT
Download-URL: https://github.com/seperman/bad-ideas/tarball/master
Platform: UNKNOWN
Classifier: Intended Audience :: Developers
Classifier: Operating System :: OS Independent
Classifier: Topic :: Software Development
Classifier: Programming Language :: Python :: 2.7
Classifier: Programming Language :: Python :: 3.3
Classifier: Programming Language :: Python :: 3.4
Classifier: Programming Language :: Python :: 3.5
Classifier: Programming Language :: Python :: Implementation :: PyPy
Classifier: Development Status :: 3 - Alpha
Classifier: License :: OSI Approved :: MIT License
